amjadsquareroot-0.1.0.dist-info/licenses/LICENSE
square_root_lib_amjad/__init__.py
square_root_lib_amjad/__main__.py
square_root_lib_amjad/core.py
amjadsquareroot-0.1.0.dist-info/METADATA
amjadsquareroot-0.1.0.dist-info/WHEEL
amjadsquareroot-0.1.0.dist-info/entry_points.txt
amjadsquareroot-0.1.0.dist-info/top_level.txt
amjadsquareroot-0.1.0.dist-info/RECORD
