Metadata-Version: 2.4
Name: AmjadSquareRoot
Version: 0.1.0
Summary: Calculate the square root of a number
Author: Amjad Sameer Alnamer
Author-email: Amjad Sameer Alnamer <aalnmr392@gmail.com>
License: MIT License
Requires-Python: >=3.7
License-File: LICENSE
Dynamic: author
Dynamic: license-file
Dynamic: requires-python
